LICENSE.txt
MANIFEST.in
README.rst
setup.py
version
src/driftwood/__init__.py
src/driftwood.egg-info/PKG-INFO
src/driftwood.egg-info/SOURCES.txt
src/driftwood.egg-info/dependency_links.txt
src/driftwood.egg-info/top_level.txt
src/driftwood/adapters/__init__.py
src/driftwood/adapters/status.py
src/driftwood/formatters/__init__.py
src/driftwood/formatters/dict.py
src/driftwood/formatters/json.py
src/driftwood/formatters/keyval.py
src/driftwood/formatters/splunk.py
src/driftwood/handlers/__init__.py
src/driftwood/handlers/dict.py
src/driftwood/handlers/mongo.py