Metadata-Version: 1.0
Name: driftwood
Version: 1.1.21
Summary: A collection of python logging extensions
Home-page: https://github.com/HurricaneLabs/driftwood
Author: Colton Leekley-Winslow
Author-email: colton@hurricanelabs.com
License: UNKNOWN
Platform: UNKNOWN
